fapyc/__init__.py
fapyc/_fapyc.cp312-win_amd64.pyd
fapyc/include/fapec_comp.h
fapyc/include/fapec_decomp.h
fapyc/include/fapec_opts.h
fapyc/lib/FapecCompress.dll
fapyc/lib/FapecCompress.lib
fapyc/lib/FapecDecompress.dll
fapyc/lib/FapecDecompress.lib
fapyc/lib/libFapecCompress.so
fapyc/lib/libFapecDecompress.so
fapyc-0.8.0.dist-info/licenses/LICENSE
fapyc-0.8.0.dist-info/METADATA
fapyc-0.8.0.dist-info/WHEEL
fapyc-0.8.0.dist-info/entry_points.txt
fapyc-0.8.0.dist-info/top_level.txt
fapyc-0.8.0.dist-info/RECORD
