Metadata-Version: 2.4
Name: fapyc
Version: 0.8.0
Summary: A Python wrapper for the FAPEC data compressor.
Author: DAPCOM Data Services
Author-email: fapec@dapcom.es
Project-URL: Homepage, https://www.dapcom.es
Project-URL: Documentation, https://www.dapcom.es/resources/fapyc/docs/index.html
License-File: LICENSE
Dynamic: description
Dynamic: description-content-type
Dynamic: license-file
Dynamic: project-url
